code_analyzer_b-0.2.4.dist-info/licenses/LICENSE
codeanalyzer/__init__.py
codeanalyzer/analyzer.py
codeanalyzer/app.py
codeanalyzer/cli.py
codeanalyzer/config.py
codeanalyzer/deepseek.py
codeanalyzer/utils.py
code_analyzer_b-0.2.4.dist-info/METADATA
code_analyzer_b-0.2.4.dist-info/WHEEL
code_analyzer_b-0.2.4.dist-info/entry_points.txt
code_analyzer_b-0.2.4.dist-info/top_level.txt
code_analyzer_b-0.2.4.dist-info/RECORD
