Metadata-Version: 2.4
Name: code-analyzer-b
Version: 0.2.4
Summary: A tool to analyze code repositories for security vulnerabilities using DeepSeek AI
Home-page: https://github.com/BotirBakhtiyarov/code_analyzer-b
Author: Botir Bakhtiyarov
Author-email: botirbakhtiyarovb@gmail.com
Classifier: Programming Language :: Python :: 3
Classifier: License :: OSI Approved :: MIT License
Classifier: Operating System :: OS Independent
Classifier: Development Status :: 4 - Beta
Classifier: Intended Audience :: Developers
Classifier: Topic :: Software Development :: Quality Assurance
Requires-Python: >=3.6
License-File: LICENSE
Requires-Dist: requests
Requires-Dist: tqdm
Dynamic: author
Dynamic: author-email
Dynamic: classifier
Dynamic: description
Dynamic: description-content-type
Dynamic: home-page
Dynamic: license-file
Dynamic: requires-dist
Dynamic: requires-python
Dynamic: summary
